request/__init__.py
request/__version__.py
request/_internal_utils.py
request/adapters.py
request/api.py
request/auth.py
request/certs.py
request/compat.py
request/cookies.py
request/exceptions.py
request/help.py
request/hooks.py
request/models.py
request/packages.py
request/sessions.py
request/status_codes.py
request/structures.py
request/utils.py
freequentsdk-2.66.1.dist-info/LICENSE
freequentsdk-2.66.1.dist-info/METADATA
freequentsdk-2.66.1.dist-info/WHEEL
freequentsdk-2.66.1.dist-info/top_level.txt
freequentsdk-2.66.1.dist-info/RECORD
